apps/__init__.py
apps/cwatcher/__init__.py
apps/cwatcher/cwatcher.py
apps/cwatcher/eval.py
apps/cwatcher/train.py
paddlespatial/__init__.py
paddlespatial/__main__.py
paddlespatial/cmdline.py
paddlespatial/demo.py
paddlespatial/datasets/__init__.py
paddlespatial/modelzoo/__init__.py
paddlespatial/networks/__init__.py
paddlespatial/networks/sagnn.py
paddlespatial/networks/vmrgae/__init__.py
paddlespatial/networks/vmrgae/agcn.py
paddlespatial/networks/vmrgae/dgcn.py
paddlespatial/networks/vmrgae/eval.py
paddlespatial/networks/vmrgae/model.py
paddlespatial/networks/vmrgae/train.py
paddlespatial/networks/vmrgae/utils.py
paddlespatial/tests/__init__.py
paddlespatial/tools/__init__.py
paddlespatial/utils/__init__.py
paddlespatial-0.1.1.dist-info/DESCRIPTION.rst
paddlespatial-0.1.1.dist-info/METADATA
paddlespatial-0.1.1.dist-info/RECORD
paddlespatial-0.1.1.dist-info/WHEEL
paddlespatial-0.1.1.dist-info/metadata.json
paddlespatial-0.1.1.dist-info/top_level.txt
tutorials/__init__.py
